setup.cfg
setup.py
magiceye_solve/__init__.py
magiceye_solve/solver.py
magiceye_solve.egg-info/PKG-INFO
magiceye_solve.egg-info/SOURCES.txt
magiceye_solve.egg-info/dependency_links.txt
magiceye_solve.egg-info/entry_points.txt
magiceye_solve.egg-info/requires.txt
magiceye_solve.egg-info/top_level.txt