Metadata-Version: 1.0
Name: magiceye-solve
Version: 0.1
Summary: Program that automatically solves magic eye autostereograms
Home-page: https://github.com/thearn/magiceye-solver
Author: Tristan Hearn
Author-email: tristanhearn@gmail.com
License: Apache 2.0
Platform: UNKNOWN
